raze3d/__init__.py
raze3d-0.1.1.dist-info/METADATA
raze3d-0.1.1.dist-info/WHEEL
raze3d-0.1.1.dist-info/top_level.txt
raze3d-0.1.1.dist-info/RECORD
