Metadata-Version: 2.4
Name: raze3d
Version: 0.1.1
Summary: Pacote 3D muito daora para usar em seus projetos Python.
Author: Davi Carozo Rocha Sobral
Classifier: Programming Language :: Python :: 3
Classifier: License :: OSI Approved :: MIT License
Classifier: Operating System :: OS Independent
Requires-Python: >=3.6
Dynamic: author
Dynamic: classifier
Dynamic: description
Dynamic: description-content-type
Dynamic: requires-python
Dynamic: summary
